{
  "time": "2026-07-18T06:08:09.799Z",
  "results": [
    {
      "name": "立播[盘]",
      "score": 75,
      "detail_success": true,
      "detail_preview": {
        "vod_name": "永远心跳漏一拍",
        "vod_play_from": "",
        "vod_play_url_count": 0,
        "play_url_diagnosis": {
          "status": "empty",
          "item_keys": [
            "vod_name",
            "vod_pic",
            "vod_content",
            "vod_play_from",
            "vod_play_url",
            "vod_play_pan",
            "vod_type",
            "vod_area",
            "vod_year",
            "vod_actor",
            "vod_director",
            "vod_total",
            "vod_score",
            "vod_remarks"
          ],
          "root_cause": "likely_tabs_or_lists_selector",
          "hint": "二级已执行(有 vod_play_from/vod_play_url 字段但值为空)。若为 dict 二级，最高频根因是 tabs 误带 &&Text(如 tabs:'.module-tab-item&&Text' 会被当 pdfa 选择器返回空导致线路循环0次)——tabs 应只写容器选择器，文本靠 tab_text(默认 body&&Text)。也需确认 tabs/lists 选择器命中站点 DOM。排查：cli debug --rule <tabs选择器> --mode pdfa --url 详情页，count 应>0。详见 references-detail-dict-and-multiep.md 第4节。"
        }
      },
      "play_success": false,
      "play_error": "二级详情已返回但 vod_play_url 为空（播放线路选择器未命中或缺 detailUrl）"
    },
    {
      "name": "樱花动漫[优]",
      "score": 90,
      "detail_success": true,
      "detail_preview": {
        "vod_id": "http://www.yinghuadm.cn/index.php/vod/detail/id/4425.html",
        "vod_name": "一拍即合的我们",
        "vod_play_from": "1-30$$$31-60$$$61-62",
        "vod_play_url_count": 60
      },
      "play_success": true,
      "play_error": null
    },
    {
      "name": "卫星影视",
      "score": 0,
      "detail_success": false,
      "detail_preview": null,
      "play_success": false,
      "play_error": "二级详情跳过(无影片ID)，无播放URL"
    },
    {
      "name": "夜猫影视",
      "score": 65,
      "detail_success": true,
      "detail_preview": {
        "vod_id": "155636",
        "vod_play_from": "",
        "vod_play_url_count": 0,
        "play_url_diagnosis": {
          "status": "empty",
          "item_keys": [
            "vod_id",
            "vod_name",
            "vod_pic",
            "type_name",
            "vod_year",
            "vod_area",
            "vod_remarks",
            "vod_actor",
            "vod_director",
            "vod_content",
            "vod_play_from",
            "vod_play_url"
          ],
          "root_cause": "likely_tabs_or_lists_selector",
          "hint": "二级已执行(有 vod_play_from/vod_play_url 字段但值为空)。若为 dict 二级，最高频根因是 tabs 误带 &&Text(如 tabs:'.module-tab-item&&Text' 会被当 pdfa 选择器返回空导致线路循环0次)——tabs 应只写容器选择器，文本靠 tab_text(默认 body&&Text)。也需确认 tabs/lists 选择器命中站点 DOM。排查：cli debug --rule <tabs选择器> --mode pdfa --url 详情页，count 应>0。详见 references-detail-dict-and-multiep.md 第4节。"
        }
      },
      "play_success": false,
      "play_error": "二级详情已返回但 vod_play_url 为空（播放线路选择器未命中或缺 detailUrl）"
    },
    {
      "name": "虎斑[盘]",
      "score": 65,
      "detail_success": true,
      "detail_preview": {
        "vod_play_from": "",
        "vod_play_url_count": 0,
        "play_url_diagnosis": {
          "status": "empty",
          "item_keys": [
            "vod_name",
            "type_name",
            "vod_pic",
            "vod_content",
            "vod_remarks",
            "vod_year",
            "vod_area",
            "vod_actor",
            "vod_director",
            "vod_play_from",
            "vod_play_url",
            "vod_play_pan"
          ],
          "root_cause": "likely_tabs_or_lists_selector",
          "hint": "二级已执行(有 vod_play_from/vod_play_url 字段但值为空)。若为 dict 二级，最高频根因是 tabs 误带 &&Text(如 tabs:'.module-tab-item&&Text' 会被当 pdfa 选择器返回空导致线路循环0次)——tabs 应只写容器选择器，文本靠 tab_text(默认 body&&Text)。也需确认 tabs/lists 选择器命中站点 DOM。排查：cli debug --rule <tabs选择器> --mode pdfa --url 详情页，count 应>0。详见 references-detail-dict-and-multiep.md 第4节。"
        }
      },
      "play_success": false,
      "play_error": "二级详情已返回但 vod_play_url 为空（播放线路选择器未命中或缺 detailUrl）"
    },
    {
      "name": "耐看点播[优]",
      "score": 65,
      "detail_success": true,
      "detail_preview": {
        "vod_id": "no_data",
        "vod_play_from": "",
        "vod_play_url_count": 0,
        "play_url_diagnosis": {
          "status": "empty",
          "item_keys": [
            "vod_id",
            "vod_name",
            "vod_pic",
            "vod_content",
            "vod_play_from",
            "vod_play_url"
          ],
          "root_cause": "likely_tabs_or_lists_selector",
          "hint": "二级已执行(有 vod_play_from/vod_play_url 字段但值为空)。若为 dict 二级，最高频根因是 tabs 误带 &&Text(如 tabs:'.module-tab-item&&Text' 会被当 pdfa 选择器返回空导致线路循环0次)——tabs 应只写容器选择器，文本靠 tab_text(默认 body&&Text)。也需确认 tabs/lists 选择器命中站点 DOM。排查：cli debug --rule <tabs选择器> --mode pdfa --url 详情页，count 应>0。详见 references-detail-dict-and-multiep.md 第4节。"
        }
      },
      "play_success": false,
      "play_error": "二级详情已返回但 vod_play_url 为空（播放线路选择器未命中或缺 detailUrl）"
    },
    {
      "name": "软鸭短剧[短]",
      "score": 65,
      "detail_success": true,
      "detail_preview": {
        "vod_name": "no_data",
        "vod_play_from": "专线",
        "vod_play_url_count": 0,
        "play_url_diagnosis": {
          "status": "empty",
          "item_keys": [
            "vod_name",
            "vod_pic",
            "vod_actor",
            "vod_remarks",
            "vod_content",
            "vod_play_from",
            "vod_play_url"
          ],
          "root_cause": "likely_tabs_or_lists_selector",
          "hint": "二级已执行(有 vod_play_from/vod_play_url 字段但值为空)。若为 dict 二级，最高频根因是 tabs 误带 &&Text(如 tabs:'.module-tab-item&&Text' 会被当 pdfa 选择器返回空导致线路循环0次)——tabs 应只写容器选择器，文本靠 tab_text(默认 body&&Text)。也需确认 tabs/lists 选择器命中站点 DOM。排查：cli debug --rule <tabs选择器> --mode pdfa --url 详情页，count 应>0。详见 references-detail-dict-and-multiep.md 第4节。"
        }
      },
      "play_success": false,
      "play_error": "二级详情已返回但 vod_play_url 为空（播放线路选择器未命中或缺 detailUrl）"
    },
    {
      "name": "无广告TV",
      "score": 65,
      "detail_success": true,
      "detail_preview": {
        "vod_id": "no_data",
        "vod_name": "片名",
        "vod_play_from": "",
        "vod_play_url_count": 0,
        "play_url_diagnosis": {
          "status": "empty",
          "item_keys": [
            "vod_id",
            "vod_name",
            "vod_pic",
            "type_name",
            "vod_year",
            "vod_area",
            "vod_remarks",
            "vod_actor",
            "vod_director",
            "vod_content",
            "vod_play_from",
            "vod_play_url"
          ],
          "root_cause": "likely_tabs_or_lists_selector",
          "hint": "二级已执行(有 vod_play_from/vod_play_url 字段但值为空)。若为 dict 二级，最高频根因是 tabs 误带 &&Text(如 tabs:'.module-tab-item&&Text' 会被当 pdfa 选择器返回空导致线路循环0次)——tabs 应只写容器选择器，文本靠 tab_text(默认 body&&Text)。也需确认 tabs/lists 选择器命中站点 DOM。排查：cli debug --rule <tabs选择器> --mode pdfa --url 详情页，count 应>0。详见 references-detail-dict-and-multiep.md 第4节。"
        }
      },
      "play_success": false,
      "play_error": "二级详情已返回但 vod_play_url 为空（播放线路选择器未命中或缺 detailUrl）"
    },
    {
      "name": "酷爱漫画[画]",
      "score": 65,
      "detail_success": true,
      "detail_preview": {
        "vod_name": "未知",
        "vod_play_from": "酷爱漫画",
        "vod_play_url_count": 1
      },
      "play_success": false,
      "play_error": "详情有 vod_play_url 但首条无法解析出 url"
    },
    {
      "name": "顶点小说[书]",
      "score": 75,
      "detail_success": true,
      "detail_preview": {
        "vod_id": "no_data",
        "vod_name": "片名",
        "vod_play_from": "",
        "vod_play_url_count": 0,
        "play_url_diagnosis": {
          "status": "empty",
          "item_keys": [
            "vod_id",
            "vod_name",
            "vod_pic",
            "type_name",
            "vod_year",
            "vod_area",
            "vod_remarks",
            "vod_actor",
            "vod_director",
            "vod_content",
            "vod_play_from",
            "vod_play_url"
          ],
          "root_cause": "likely_tabs_or_lists_selector",
          "hint": "二级已执行(有 vod_play_from/vod_play_url 字段但值为空)。若为 dict 二级，最高频根因是 tabs 误带 &&Text(如 tabs:'.module-tab-item&&Text' 会被当 pdfa 选择器返回空导致线路循环0次)——tabs 应只写容器选择器，文本靠 tab_text(默认 body&&Text)。也需确认 tabs/lists 选择器命中站点 DOM。排查：cli debug --rule <tabs选择器> --mode pdfa --url 详情页，count 应>0。详见 references-detail-dict-and-multiep.md 第4节。"
        }
      },
      "play_success": false,
      "play_error": "二级详情已返回但 vod_play_url 为空（播放线路选择器未命中或缺 detailUrl）"
    },
    {
      "name": "木偶[盘]",
      "score": 75,
      "detail_success": true,
      "detail_preview": {
        "vod_name": "加载失败",
        "vod_play_from": "加载错误$$$所有链接无效",
        "vod_play_url_count": 1
      },
      "play_success": false,
      "play_error": "详情有 vod_play_url 但首条无法解析出 url"
    }
  ]
}